{
  "schemaVersion": "2.0",
  "generatedAt": "2026-05-25T22:35:15.157Z",
  "date": "today",
  "stadium": "10",
  "stadiumName": null,
  "race": "2R",
  "deadline": "2026-05-26 09:05:00",
  "gradeNumber": 5,
  "title": "三国巧者決定戦",
  "subtitle": "みくにあさガチ",
  "distance": 1800,
  "entries": [
    {
      "lane": 1,
      "number": 5028,
      "name": "原田 才一郎",
      "classNumber": 1,
      "branchNumber": 40,
      "birthplaceNumber": 40,
      "age": 29,
      "weight": 52,
      "flyingCount": 0,
      "lateCount": 0,
      "avgST": 0.16,
      "natTop1": 6.68,
      "natTop2": 50.55,
      "natTop3": 68.13,
      "locTop1": 6.86,
      "locTop2": 51.72,
      "locTop3": 68.97,
      "motorNumber": 49,
      "motorTop2": 33.33,
      "motorTop3": 44.44,
      "boatNumber": 65,
      "boatTop2": 24.44,
      "boatTop3": 53.33
    },
    {
      "lane": 2,
      "number": 4079,
      "name": "出畑 孝典",
      "classNumber": 2,
      "branchNumber": 40,
      "birthplaceNumber": 40,
      "age": 47,
      "weight": 51,
      "flyingCount": 0,
      "lateCount": 0,
      "avgST": 0.16,
      "natTop1": 5.61,
      "natTop2": 35.24,
      "natTop3": 58.1,
      "locTop1": 7.08,
      "locTop2": 46.15,
      "locTop3": 84.62,
      "motorNumber": 29,
      "motorTop2": 23.26,
      "motorTop3": 39.53,
      "boatNumber": 24,
      "boatTop2": 34.88,
      "boatTop3": 60.47
    },
    {
      "lane": 3,
      "number": 3319,
      "name": "山崎 義明",
      "classNumber": 3,
      "branchNumber": 11,
      "birthplaceNumber": 11,
      "age": 59,
      "weight": 52,
      "flyingCount": 0,
      "lateCount": 0,
      "avgST": 0.17,
      "natTop1": 5.39,
      "natTop2": 35.51,
      "natTop3": 56.07,
      "locTop1": 4.56,
      "locTop2": 22.22,
      "locTop3": 38.89,
      "motorNumber": 52,
      "motorTop2": 30.43,
      "motorTop3": 43.48,
      "boatNumber": 44,
      "boatTop2": 50,
      "boatTop3": 66.67
    },
    {
      "lane": 4,
      "number": 4782,
      "name": "浜崎 準也",
      "classNumber": 3,
      "branchNumber": 33,
      "birthplaceNumber": 33,
      "age": 39,
      "weight": 52,
      "flyingCount": 1,
      "lateCount": 0,
      "avgST": 0.18,
      "natTop1": 4.31,
      "natTop2": 19.35,
      "natTop3": 38.71,
      "locTop1": 6.18,
      "locTop2": 45.45,
      "locTop3": 63.64,
      "motorNumber": 65,
      "motorTop2": 50,
      "motorTop3": 66.67,
      "boatNumber": 32,
      "boatTop2": 29.55,
      "boatTop3": 45.45
    },
    {
      "lane": 5,
      "number": 3929,
      "name": "杢野 誓良",
      "classNumber": 3,
      "branchNumber": 23,
      "birthplaceNumber": 23,
      "age": 50,
      "weight": 51.5,
      "flyingCount": 0,
      "lateCount": 0,
      "avgST": 0.16,
      "natTop1": 4.13,
      "natTop2": 20,
      "natTop3": 35.56,
      "locTop1": 5.37,
      "locTop2": 30.23,
      "locTop3": 53.49,
      "motorNumber": 68,
      "motorTop2": 17.07,
      "motorTop3": 31.71,
      "boatNumber": 27,
      "boatTop2": 30.23,
      "boatTop3": 53.49
    },
    {
      "lane": 6,
      "number": 3832,
      "name": "下田 哲也",
      "classNumber": 3,
      "branchNumber": 37,
      "birthplaceNumber": 37,
      "age": 51,
      "weight": 54.8,
      "flyingCount": 0,
      "lateCount": 0,
      "avgST": 0.16,
      "natTop1": 3.13,
      "natTop2": 9.38,
      "natTop3": 15.63,
      "locTop1": 4.89,
      "locTop2": 22.22,
      "locTop3": 44.44,
      "motorNumber": 59,
      "motorTop2": 26.19,
      "motorTop3": 54.76,
      "boatNumber": 45,
      "boatTop2": 15.91,
      "boatTop3": 45.45
    }
  ]
}