{
  "date": "20250826",
  "pid": "06",
  "race": "3R",
  "source": "https://www.boatrace.jp/owpc/pc/race/beforeinfo?hd=20250826&jcd=06&rno=3",
  "mode": "beforeinfo",
  "generatedAt": "2025-08-26T03:31:27.639Z",
  "weather": {
    "weather": "晴",
    "temperature": 28,
    "windSpeed": 3,
    "windDirection": "西",
    "waterTemperature": 28,
    "waveHeight": 0.01,
    "stabilizer": false
  },
  "entries": [
    {
      "lane": 1,
      "number": "5261",
      "name": "岡 暢祐",
      "weight": "52.0kg",
      "tenjiTime": "6.72",
      "tilt": "0.0",
      "st": ".12",
      "stFlag": ""
    },
    {
      "lane": 2,
      "number": "4457",
      "name": "神田 達也",
      "weight": "52.2kg",
      "tenjiTime": "6.74",
      "tilt": "0.0",
      "st": "F.02",
      "stFlag": "F"
    },
    {
      "lane": 3,
      "number": "4062",
      "name": "後藤 陽介",
      "weight": "55.7kg",
      "tenjiTime": "6.71",
      "tilt": "-0.5",
      "st": ".08",
      "stFlag": ""
    },
    {
      "lane": 4,
      "number": "4023",
      "name": "柴田 友和",
      "weight": "52.0kg",
      "tenjiTime": "6.69",
      "tilt": "-0.5",
      "st": ".29",
      "stFlag": ""
    },
    {
      "lane": 5,
      "number": "3548",
      "name": "室田 泰史",
      "weight": "52.0kg",
      "tenjiTime": "6.72",
      "tilt": "-0.5",
      "st": ".18",
      "stFlag": ""
    },
    {
      "lane": 6,
      "number": "4677",
      "name": "片橋 幸貴",
      "weight": "52.3kg",
      "tenjiTime": "6.59",
      "tilt": "0.0",
      "st": ".28",
      "stFlag": ""
    }
  ]
}