{
  "schemaVersion": "2.0",
  "generatedAt": "2025-11-09T21:38:42.178Z",
  "date": "today",
  "stadium": "09",
  "stadiumName": null,
  "race": "2R",
  "deadline": "2025-11-10 10:57:00",
  "gradeNumber": 5,
  "title": "エキサイティング・スポー津カップ",
  "subtitle": "一般",
  "distance": 1800,
  "entries": [
    {
      "lane": 1,
      "number": 4181,
      "name": "花本 夏樹",
      "classNumber": 3,
      "branchNumber": 24,
      "birthplaceNumber": 24,
      "age": 42,
      "weight": 53.6,
      "flyingCount": 0,
      "lateCount": 0,
      "avgST": 0.18,
      "natTop1": 4.23,
      "natTop2": 22.22,
      "natTop3": 38.27,
      "locTop1": 4.54,
      "locTop2": 22.22,
      "locTop3": 37.3,
      "motorNumber": 27,
      "motorTop2": 34.31,
      "motorTop3": 49.02,
      "boatNumber": 76,
      "boatTop2": 29.89,
      "boatTop3": 48.37
    },
    {
      "lane": 2,
      "number": 4041,
      "name": "小林 基樹",
      "classNumber": 3,
      "branchNumber": 35,
      "birthplaceNumber": 35,
      "age": 46,
      "weight": 53.3,
      "flyingCount": 0,
      "lateCount": 0,
      "avgST": 0.22,
      "natTop1": 4.5,
      "natTop2": 25,
      "natTop3": 38.89,
      "locTop1": 5.07,
      "locTop2": 33.33,
      "locTop3": 55.56,
      "motorNumber": 45,
      "motorTop2": 29.69,
      "motorTop3": 48.96,
      "boatNumber": 35,
      "boatTop2": 39.7,
      "boatTop3": 53.77
    },
    {
      "lane": 3,
      "number": 5128,
      "name": "坪井 爽佑",
      "classNumber": 4,
      "branchNumber": 24,
      "birthplaceNumber": 24,
      "age": 28,
      "weight": 52.3,
      "flyingCount": 0,
      "lateCount": 0,
      "avgST": 0.2,
      "natTop1": 4.07,
      "natTop2": 27.78,
      "natTop3": 35.19,
      "locTop1": 3.93,
      "locTop2": 25.35,
      "locTop3": 32.39,
      "motorNumber": 12,
      "motorTop2": 39.3,
      "motorTop3": 57.21,
      "boatNumber": 36,
      "boatTop2": 27.78,
      "boatTop3": 44.44
    },
    {
      "lane": 4,
      "number": 3718,
      "name": "伊達 正利",
      "classNumber": 3,
      "branchNumber": 22,
      "birthplaceNumber": 22,
      "age": 50,
      "weight": 54.1,
      "flyingCount": 0,
      "lateCount": 0,
      "avgST": 0.19,
      "natTop1": 4.34,
      "natTop2": 23.08,
      "natTop3": 35.16,
      "locTop1": 4.31,
      "locTop2": 26.92,
      "locTop3": 46.15,
      "motorNumber": 48,
      "motorTop2": 32.21,
      "motorTop3": 55.29,
      "boatNumber": 28,
      "boatTop2": 32.5,
      "boatTop3": 45
    },
    {
      "lane": 5,
      "number": 5244,
      "name": "黒田 剛",
      "classNumber": 3,
      "branchNumber": 40,
      "birthplaceNumber": 40,
      "age": 25,
      "weight": 52,
      "flyingCount": 0,
      "lateCount": 0,
      "avgST": 0.17,
      "natTop1": 3.55,
      "natTop2": 7.32,
      "natTop3": 28.05,
      "locTop1": 4.53,
      "locTop2": 23.53,
      "locTop3": 41.18,
      "motorNumber": 46,
      "motorTop2": 33.49,
      "motorTop3": 53.49,
      "boatNumber": 34,
      "boatTop2": 34.27,
      "boatTop3": 48.83
    },
    {
      "lane": 6,
      "number": 5425,
      "name": "西山 育",
      "classNumber": 4,
      "branchNumber": 24,
      "birthplaceNumber": 24,
      "age": 23,
      "weight": 54.5,
      "flyingCount": 0,
      "lateCount": 0,
      "avgST": null,
      "natTop1": 0,
      "natTop2": 0,
      "natTop3": 0,
      "locTop1": 0,
      "locTop2": 0,
      "locTop3": 0,
      "motorNumber": 59,
      "motorTop2": 29.87,
      "motorTop3": 39.83,
      "boatNumber": 59,
      "boatTop2": 33.16,
      "boatTop3": 46.94
    }
  ]
}