{
  "schemaVersion": "2.0",
  "generatedAt": "2025-10-24T21:38:55.467Z",
  "date": "today",
  "stadium": "09",
  "stadiumName": null,
  "race": "3R",
  "deadline": "2025-10-25 11:34:00",
  "gradeNumber": 1,
  "title": "第72回ボートレースダービー",
  "subtitle": "一般",
  "distance": 1800,
  "entries": [
    {
      "lane": 1,
      "number": 4544,
      "name": "松田 大志郎",
      "classNumber": 1,
      "branchNumber": 40,
      "birthplaceNumber": 40,
      "age": 37,
      "weight": 52,
      "flyingCount": 0,
      "lateCount": 0,
      "avgST": 0.17,
      "natTop1": 7.97,
      "natTop2": 71.74,
      "natTop3": 82.61,
      "locTop1": 8.45,
      "locTop2": 72.73,
      "locTop3": 95.45,
      "motorNumber": 15,
      "motorTop2": 37.02,
      "motorTop3": 57.46,
      "boatNumber": 26,
      "boatTop2": 35,
      "boatTop3": 51.43
    },
    {
      "lane": 2,
      "number": 4851,
      "name": "関 浩哉",
      "classNumber": 1,
      "branchNumber": 10,
      "birthplaceNumber": 10,
      "age": 30,
      "weight": 50.5,
      "flyingCount": 0,
      "lateCount": 0,
      "avgST": 0.14,
      "natTop1": 7.5,
      "natTop2": 50.85,
      "natTop3": 70.34,
      "locTop1": 7.67,
      "locTop2": 44.44,
      "locTop3": 77.78,
      "motorNumber": 58,
      "motorTop2": 29.1,
      "motorTop3": 41.27,
      "boatNumber": 76,
      "boatTop2": 30.29,
      "boatTop3": 48.57
    },
    {
      "lane": 3,
      "number": 4357,
      "name": "田中 和也",
      "classNumber": 1,
      "branchNumber": 27,
      "birthplaceNumber": 27,
      "age": 41,
      "weight": 52,
      "flyingCount": 0,
      "lateCount": 0,
      "avgST": 0.17,
      "natTop1": 6.89,
      "natTop2": 56.52,
      "natTop3": 71.3,
      "locTop1": 6.15,
      "locTop2": 30.77,
      "locTop3": 69.23,
      "motorNumber": 32,
      "motorTop2": 34.56,
      "motorTop3": 52.07,
      "boatNumber": 59,
      "boatTop2": 34.62,
      "boatTop3": 48.9
    },
    {
      "lane": 4,
      "number": 4208,
      "name": "三浦 永理",
      "classNumber": 1,
      "branchNumber": 22,
      "birthplaceNumber": 22,
      "age": 42,
      "weight": 47,
      "flyingCount": 0,
      "lateCount": 0,
      "avgST": 0.15,
      "natTop1": 6.61,
      "natTop2": 44.55,
      "natTop3": 67.27,
      "locTop1": 6.89,
      "locTop2": 47.83,
      "locTop3": 65.22,
      "motorNumber": 29,
      "motorTop2": 42.22,
      "motorTop3": 60.56,
      "boatNumber": 34,
      "boatTop2": 34.34,
      "boatTop3": 48.99
    },
    {
      "lane": 5,
      "number": 4547,
      "name": "中田 竜太",
      "classNumber": 1,
      "branchNumber": 11,
      "birthplaceNumber": 7,
      "age": 37,
      "weight": 51.5,
      "flyingCount": 1,
      "lateCount": 0,
      "avgST": 0.16,
      "natTop1": 6.83,
      "natTop2": 52.03,
      "natTop3": 65.04,
      "locTop1": 6.11,
      "locTop2": 27.78,
      "locTop3": 61.11,
      "motorNumber": 73,
      "motorTop2": 32.35,
      "motorTop3": 51.96,
      "boatNumber": 55,
      "boatTop2": 33.89,
      "boatTop3": 45.56
    },
    {
      "lane": 6,
      "number": 4686,
      "name": "丸野 一樹",
      "classNumber": 1,
      "branchNumber": 25,
      "birthplaceNumber": 13,
      "age": 34,
      "weight": 53.1,
      "flyingCount": 0,
      "lateCount": 0,
      "avgST": 0.16,
      "natTop1": 7.65,
      "natTop2": 51.3,
      "natTop3": 69.57,
      "locTop1": 5.83,
      "locTop2": 50,
      "locTop3": 66.67,
      "motorNumber": 53,
      "motorTop2": 31.22,
      "motorTop3": 49.27,
      "boatNumber": 56,
      "boatTop2": 33.71,
      "boatTop3": 47.43
    }
  ]
}