{
  "schemaVersion": "2.0",
  "generatedAt": "2026-03-23T21:57:20.529Z",
  "date": "today",
  "stadium": "09",
  "stadiumName": null,
  "race": "6R",
  "deadline": "2026-03-24 12:53:00",
  "gradeNumber": 5,
  "title": "BTS養老開設9周年記念よーたんカップ",
  "subtitle": "予選",
  "distance": 1800,
  "entries": [
    {
      "lane": 1,
      "number": 4169,
      "name": "多田 有佑",
      "classNumber": 3,
      "branchNumber": 13,
      "birthplaceNumber": 6,
      "age": 43,
      "weight": 54.4,
      "flyingCount": 1,
      "lateCount": 0,
      "avgST": 0.21,
      "natTop1": 3.46,
      "natTop2": 15.28,
      "natTop3": 23.61,
      "locTop1": 4,
      "locTop2": 22.22,
      "locTop3": 27.78,
      "motorNumber": 49,
      "motorTop2": 25,
      "motorTop3": 39.29,
      "boatNumber": 48,
      "boatTop2": 55.56,
      "boatTop3": 70.37
    },
    {
      "lane": 2,
      "number": 4380,
      "name": "鈴木 峻佑",
      "classNumber": 3,
      "branchNumber": 22,
      "birthplaceNumber": 22,
      "age": 41,
      "weight": 52.5,
      "flyingCount": 0,
      "lateCount": 0,
      "avgST": 0.17,
      "natTop1": 4.27,
      "natTop2": 21.95,
      "natTop3": 32.93,
      "locTop1": 2.4,
      "locTop2": 0,
      "locTop3": 20,
      "motorNumber": 59,
      "motorTop2": 20,
      "motorTop3": 42.5,
      "boatNumber": 59,
      "boatTop2": 30.3,
      "boatTop3": 45.45
    },
    {
      "lane": 3,
      "number": 4738,
      "name": "清埜 翔子",
      "classNumber": 2,
      "branchNumber": 11,
      "birthplaceNumber": 11,
      "age": 34,
      "weight": 47.1,
      "flyingCount": 0,
      "lateCount": 0,
      "avgST": 0.16,
      "natTop1": 5.69,
      "natTop2": 38.76,
      "natTop3": 55.81,
      "locTop1": 5.4,
      "locTop2": 30,
      "locTop3": 40,
      "motorNumber": 65,
      "motorTop2": 25.93,
      "motorTop3": 44.44,
      "boatNumber": 36,
      "boatTop2": 28.57,
      "boatTop3": 57.14
    },
    {
      "lane": 4,
      "number": 5111,
      "name": "三村 岳人",
      "classNumber": 4,
      "branchNumber": 33,
      "birthplaceNumber": 33,
      "age": 26,
      "weight": 50.9,
      "flyingCount": 0,
      "lateCount": 0,
      "avgST": 0.19,
      "natTop1": 5.05,
      "natTop2": 36.27,
      "natTop3": 50,
      "locTop1": 5.82,
      "locTop2": 45.45,
      "locTop3": 63.64,
      "motorNumber": 28,
      "motorTop2": 25,
      "motorTop3": 46.43,
      "boatNumber": 20,
      "boatTop2": 29.41,
      "boatTop3": 44.12
    },
    {
      "lane": 5,
      "number": 5382,
      "name": "山下 心一",
      "classNumber": 3,
      "branchNumber": 40,
      "birthplaceNumber": 40,
      "age": 21,
      "weight": 53.3,
      "flyingCount": 1,
      "lateCount": 0,
      "avgST": 0.16,
      "natTop1": 2.47,
      "natTop2": 3.45,
      "natTop3": 12.07,
      "locTop1": 0,
      "locTop2": 0,
      "locTop3": 0,
      "motorNumber": 43,
      "motorTop2": 16,
      "motorTop3": 32,
      "boatNumber": 73,
      "boatTop2": 23.33,
      "boatTop3": 53.33
    },
    {
      "lane": 6,
      "number": 3854,
      "name": "吉川 元浩",
      "classNumber": 1,
      "branchNumber": 28,
      "birthplaceNumber": 28,
      "age": 53,
      "weight": 51.3,
      "flyingCount": 1,
      "lateCount": 0,
      "avgST": 0.13,
      "natTop1": 6.58,
      "natTop2": 42.45,
      "natTop3": 63.21,
      "locTop1": 5.62,
      "locTop2": 30.77,
      "locTop3": 46.15,
      "motorNumber": 45,
      "motorTop2": 4.17,
      "motorTop3": 20.83,
      "boatNumber": 38,
      "boatTop2": 41.38,
      "boatTop3": 58.62
    }
  ]
}