{
  "schemaVersion": "2.0",
  "generatedAt": "2025-11-10T21:41:01.457Z",
  "date": "today",
  "stadium": "03",
  "stadiumName": null,
  "race": "11R",
  "deadline": "2025-11-11 15:27:00",
  "gradeNumber": 5,
  "title": "月兎ソースカップ",
  "subtitle": "準優勝戦",
  "distance": 1800,
  "entries": [
    {
      "lane": 1,
      "number": 4264,
      "name": "長尾 章平",
      "classNumber": 1,
      "branchNumber": 35,
      "birthplaceNumber": 35,
      "age": 40,
      "weight": 52.8,
      "flyingCount": 0,
      "lateCount": 0,
      "avgST": 0.16,
      "natTop1": 6.5,
      "natTop2": 50.37,
      "natTop3": 67.41,
      "locTop1": 0,
      "locTop2": 0,
      "locTop3": 0,
      "motorNumber": 27,
      "motorTop2": 31.48,
      "motorTop3": 44.44,
      "boatNumber": 58,
      "boatTop2": 40,
      "boatTop3": 51.82
    },
    {
      "lane": 2,
      "number": 4624,
      "name": "高田 明",
      "classNumber": 2,
      "branchNumber": 41,
      "birthplaceNumber": 41,
      "age": 40,
      "weight": 51.5,
      "flyingCount": 0,
      "lateCount": 0,
      "avgST": 0.18,
      "natTop1": 6.73,
      "natTop2": 51.67,
      "natTop3": 71.67,
      "locTop1": 7.36,
      "locTop2": 61.11,
      "locTop3": 80.56,
      "motorNumber": 60,
      "motorTop2": 35.45,
      "motorTop3": 53.64,
      "boatNumber": 23,
      "boatTop2": 40.57,
      "boatTop3": 58.49
    },
    {
      "lane": 3,
      "number": 4471,
      "name": "新田 泰章",
      "classNumber": 1,
      "branchNumber": 34,
      "birthplaceNumber": 34,
      "age": 38,
      "weight": 52.5,
      "flyingCount": 0,
      "lateCount": 0,
      "avgST": 0.16,
      "natTop1": 7.13,
      "natTop2": 56.78,
      "natTop3": 77.97,
      "locTop1": 6.58,
      "locTop2": 54.84,
      "locTop3": 74.19,
      "motorNumber": 49,
      "motorTop2": 44.23,
      "motorTop3": 60.58,
      "boatNumber": 24,
      "boatTop2": 29.13,
      "boatTop3": 51.46
    },
    {
      "lane": 4,
      "number": 4118,
      "name": "宇佐見 淳",
      "classNumber": 1,
      "branchNumber": 23,
      "birthplaceNumber": 23,
      "age": 44,
      "weight": 52,
      "flyingCount": 0,
      "lateCount": 0,
      "avgST": 0.15,
      "natTop1": 6.6,
      "natTop2": 48,
      "natTop3": 68,
      "locTop1": 6.19,
      "locTop2": 46.55,
      "locTop3": 62.07,
      "motorNumber": 36,
      "motorTop2": 44.86,
      "motorTop3": 56.07,
      "boatNumber": 28,
      "boatTop2": 36,
      "boatTop3": 53
    },
    {
      "lane": 5,
      "number": 5257,
      "name": "西丸 侑太朗",
      "classNumber": 2,
      "branchNumber": 37,
      "birthplaceNumber": 37,
      "age": 21,
      "weight": 53.2,
      "flyingCount": 0,
      "lateCount": 0,
      "avgST": 0.18,
      "natTop1": 6.66,
      "natTop2": 50.5,
      "natTop3": 65.35,
      "locTop1": 3.93,
      "locTop2": 18.6,
      "locTop3": 32.56,
      "motorNumber": 54,
      "motorTop2": 24.3,
      "motorTop3": 40.19,
      "boatNumber": 29,
      "boatTop2": 40.19,
      "boatTop3": 59.81
    },
    {
      "lane": 6,
      "number": 3868,
      "name": "尾形 栄治",
      "classNumber": 3,
      "branchNumber": 13,
      "birthplaceNumber": 13,
      "age": 50,
      "weight": 54.4,
      "flyingCount": 0,
      "lateCount": 0,
      "avgST": 0.18,
      "natTop1": 4.03,
      "natTop2": 20.25,
      "natTop3": 32.91,
      "locTop1": 4.94,
      "locTop2": 26.32,
      "locTop3": 48.42,
      "motorNumber": 56,
      "motorTop2": 47.52,
      "motorTop3": 62.38,
      "boatNumber": 70,
      "boatTop2": 32.38,
      "boatTop3": 55.24
    }
  ]
}