{
  "schemaVersion": "2.0",
  "generatedAt": "2025-12-31T21:41:32.984Z",
  "date": "today",
  "stadium": "20",
  "stadiumName": null,
  "race": "12R",
  "deadline": "2026-01-01 20:30:00",
  "gradeNumber": 5,
  "title": "スポーツ報知杯年始特選競走",
  "subtitle": "ドリーム戦",
  "distance": 1800,
  "entries": [
    {
      "lane": 1,
      "number": 4566,
      "name": "塩田 北斗",
      "classNumber": 1,
      "branchNumber": 40,
      "birthplaceNumber": 40,
      "age": 38,
      "weight": 53.7,
      "flyingCount": 0,
      "lateCount": 0,
      "avgST": 0.14,
      "natTop1": 6.68,
      "natTop2": 38.94,
      "natTop3": 58.41,
      "locTop1": 7.83,
      "locTop2": 64.29,
      "locTop3": 78.57,
      "motorNumber": 50,
      "motorTop2": 26.32,
      "motorTop3": 42.11,
      "boatNumber": 13,
      "boatTop2": 34.17,
      "boatTop3": 54.17
    },
    {
      "lane": 2,
      "number": 4287,
      "name": "今井 貴士",
      "classNumber": 1,
      "branchNumber": 40,
      "birthplaceNumber": 40,
      "age": 41,
      "weight": 57.5,
      "flyingCount": 0,
      "lateCount": 0,
      "avgST": 0.17,
      "natTop1": 5.8,
      "natTop2": 42.11,
      "natTop3": 52.63,
      "locTop1": 6.87,
      "locTop2": 61.7,
      "locTop3": 70.21,
      "motorNumber": 13,
      "motorTop2": 36.84,
      "motorTop3": 52.63,
      "boatNumber": 69,
      "boatTop2": 30.83,
      "boatTop3": 47.37
    },
    {
      "lane": 3,
      "number": 3576,
      "name": "白水 勝也",
      "classNumber": 1,
      "branchNumber": 40,
      "birthplaceNumber": 40,
      "age": 53,
      "weight": 51.7,
      "flyingCount": 0,
      "lateCount": 0,
      "avgST": 0.17,
      "natTop1": 6.63,
      "natTop2": 48.45,
      "natTop3": 73.2,
      "locTop1": 6.4,
      "locTop2": 45,
      "locTop3": 65,
      "motorNumber": 40,
      "motorTop2": 33.33,
      "motorTop3": 55.56,
      "boatNumber": 14,
      "boatTop2": 38.76,
      "boatTop3": 51.16
    },
    {
      "lane": 4,
      "number": 4364,
      "name": "池永 太",
      "classNumber": 1,
      "branchNumber": 40,
      "birthplaceNumber": 45,
      "age": 40,
      "weight": 54,
      "flyingCount": 0,
      "lateCount": 0,
      "avgST": 0.14,
      "natTop1": 7.03,
      "natTop2": 57.63,
      "natTop3": 75.42,
      "locTop1": 7.61,
      "locTop2": 66.67,
      "locTop3": 77.78,
      "motorNumber": 51,
      "motorTop2": 33.33,
      "motorTop3": 50,
      "boatNumber": 18,
      "boatTop2": 32.5,
      "boatTop3": 48.33
    },
    {
      "lane": 5,
      "number": 4155,
      "name": "長野 壮志郎",
      "classNumber": 1,
      "branchNumber": 40,
      "birthplaceNumber": 40,
      "age": 45,
      "weight": 56.2,
      "flyingCount": 0,
      "lateCount": 0,
      "avgST": 0.16,
      "natTop1": 6.31,
      "natTop2": 46.43,
      "natTop3": 65.48,
      "locTop1": 7.17,
      "locTop2": 60,
      "locTop3": 80,
      "motorNumber": 17,
      "motorTop2": 26.32,
      "motorTop3": 42.11,
      "boatNumber": 42,
      "boatTop2": 35.66,
      "boatTop3": 55.04
    },
    {
      "lane": 6,
      "number": 5018,
      "name": "竹下 大樹",
      "classNumber": 1,
      "branchNumber": 40,
      "birthplaceNumber": 40,
      "age": 26,
      "weight": 54.7,
      "flyingCount": 0,
      "lateCount": 0,
      "avgST": 0.16,
      "natTop1": 6.53,
      "natTop2": 51.69,
      "natTop3": 67.8,
      "locTop1": 6.19,
      "locTop2": 48.08,
      "locTop3": 57.69,
      "motorNumber": 25,
      "motorTop2": 26.32,
      "motorTop3": 42.11,
      "boatNumber": 15,
      "boatTop2": 41.46,
      "boatTop3": 59.35
    }
  ]
}