{
  "schemaVersion": "2.0",
  "generatedAt": "2026-04-16T22:08:00.160Z",
  "date": "today",
  "stadium": "20",
  "stadiumName": null,
  "race": "1R",
  "deadline": "2026-04-17 15:18:00",
  "gradeNumber": 5,
  "title": "北九州市長杯Mooovi・Gruun開設記念競走",
  "subtitle": "予選",
  "distance": 1800,
  "entries": [
    {
      "lane": 1,
      "number": 3998,
      "name": "冨成 謙児",
      "classNumber": 3,
      "branchNumber": 41,
      "birthplaceNumber": 41,
      "age": 46,
      "weight": 52.3,
      "flyingCount": 0,
      "lateCount": 0,
      "avgST": 0.17,
      "natTop1": 4.35,
      "natTop2": 23.46,
      "natTop3": 35.8,
      "locTop1": 4.9,
      "locTop2": 30,
      "locTop3": 46.67,
      "motorNumber": 21,
      "motorTop2": 38.03,
      "motorTop3": 56.34,
      "boatNumber": 45,
      "boatTop2": 37.78,
      "boatTop3": 53.33
    },
    {
      "lane": 2,
      "number": 5259,
      "name": "野田 昇吾",
      "classNumber": 3,
      "branchNumber": 11,
      "birthplaceNumber": 40,
      "age": 32,
      "weight": 55.7,
      "flyingCount": 0,
      "lateCount": 0,
      "avgST": 0.15,
      "natTop1": 3,
      "natTop2": 9.38,
      "natTop3": 12.5,
      "locTop1": 0,
      "locTop2": 0,
      "locTop3": 0,
      "motorNumber": 24,
      "motorTop2": 29.87,
      "motorTop3": 44.16,
      "boatNumber": 54,
      "boatTop2": 41.62,
      "boatTop3": 57.3
    },
    {
      "lane": 3,
      "number": 4677,
      "name": "片橋 幸貴",
      "classNumber": 4,
      "branchNumber": 25,
      "birthplaceNumber": 13,
      "age": 37,
      "weight": 54,
      "flyingCount": 0,
      "lateCount": 0,
      "avgST": 0.2,
      "natTop1": 6.61,
      "natTop2": 45.78,
      "natTop3": 72.29,
      "locTop1": 6.71,
      "locTop2": 50,
      "locTop3": 54.17,
      "motorNumber": 50,
      "motorTop2": 35.21,
      "motorTop3": 52.11,
      "boatNumber": 55,
      "boatTop2": 37.36,
      "boatTop3": 56.59
    },
    {
      "lane": 4,
      "number": 4861,
      "name": "田中 宏樹",
      "classNumber": 3,
      "branchNumber": 40,
      "birthplaceNumber": 45,
      "age": 37,
      "weight": 52.2,
      "flyingCount": 0,
      "lateCount": 0,
      "avgST": 0.18,
      "natTop1": 5.74,
      "natTop2": 38.71,
      "natTop3": 60.22,
      "locTop1": 5.09,
      "locTop2": 31.34,
      "locTop3": 47.76,
      "motorNumber": 17,
      "motorTop2": 29.73,
      "motorTop3": 45.95,
      "boatNumber": 44,
      "boatTop2": 45.81,
      "boatTop3": 68.72
    },
    {
      "lane": 5,
      "number": 3508,
      "name": "久富 政弘",
      "classNumber": 3,
      "branchNumber": 41,
      "birthplaceNumber": 41,
      "age": 54,
      "weight": 53.3,
      "flyingCount": 0,
      "lateCount": 0,
      "avgST": 0.19,
      "natTop1": 5.53,
      "natTop2": 33.33,
      "natTop3": 55.56,
      "locTop1": 5.7,
      "locTop2": 34.78,
      "locTop3": 56.52,
      "motorNumber": 38,
      "motorTop2": 25,
      "motorTop3": 43.75,
      "boatNumber": 21,
      "boatTop2": 34.3,
      "boatTop3": 52.33
    },
    {
      "lane": 6,
      "number": 4866,
      "name": "橋本 英一",
      "classNumber": 3,
      "branchNumber": 40,
      "birthplaceNumber": 40,
      "age": 36,
      "weight": 52.6,
      "flyingCount": 1,
      "lateCount": 0,
      "avgST": 0.16,
      "natTop1": 4.24,
      "natTop2": 16.67,
      "natTop3": 39.39,
      "locTop1": 3.68,
      "locTop2": 16.13,
      "locTop3": 29.03,
      "motorNumber": 23,
      "motorTop2": 47.95,
      "motorTop3": 69.86,
      "boatNumber": 42,
      "boatTop2": 35.52,
      "boatTop3": 55.19
    }
  ]
}