{
  "date": "20250809",
  "pid": "20",
  "race": "9R",
  "source": {
    "result": "https://www.boatrace.jp/owpc/pc/race/raceresult?rno=9&jcd=20&hd=20250809"
  },
  "generatedAt": "2025-08-14T20:57:33.183Z",
  "order": [
    {
      "pos": 1,
      "lane": 6,
      "racerId": "4594",
      "name": "谷川 祐一",
      "time": "1'51\"7"
    },
    {
      "pos": 2,
      "lane": 4,
      "racerId": "4615",
      "name": "板倉 敦史",
      "time": "1'52\"6"
    },
    {
      "pos": 3,
      "lane": 2,
      "racerId": "3701",
      "name": "大西 隆洋",
      "time": "1'55\"1"
    },
    {
      "pos": 4,
      "lane": 3,
      "racerId": "4323",
      "name": "山田 佑樹",
      "time": "1'56\"0"
    },
    {
      "pos": 5,
      "lane": 1,
      "racerId": "4136",
      "name": "江夏 満",
      "time": ""
    },
    {
      "pos": 6,
      "lane": 5,
      "racerId": "3869",
      "name": "井芹 大志",
      "time": ""
    }
  ],
  "start": [
    {
      "lane": 1,
      "st": 0.14
    },
    {
      "lane": 2,
      "st": 0.17
    },
    {
      "lane": 3,
      "st": 0.09
    },
    {
      "lane": 6,
      "st": 0.05
    },
    {
      "lane": 4,
      "st": 0.14
    },
    {
      "lane": 5,
      "st": 0.16
    }
  ],
  "decision": "まくり",
  "weather": {
    "condition": "雨",
    "airTemp": 24,
    "windSpeed": 5,
    "windDirCode": 4,
    "waterTemp": 26,
    "wave": 5
  },
  "refunds": [],
  "payouts": {
    "trifecta": {
      "combo": "6-4-2",
      "amount": 30030,
      "popularity": 52
    },
    "trio": {
      "combo": "2=4=6",
      "amount": 8400,
      "popularity": 14
    },
    "exacta": {
      "combo": "6-4",
      "amount": 3210,
      "popularity": 8
    },
    "quinella": {
      "combo": "4=6",
      "amount": 2290,
      "popularity": 7
    },
    "wide": [
      {
        "combo": "4=6",
        "amount": 510,
        "popularity": 7
      },
      {
        "combo": "1=120",
        "amount": 11,
        "popularity": null
      }
    ],
    "win": {
      "combo": "6",
      "amount": 320
    },
    "place": [
      {
        "combo": "6",
        "amount": 190
      }
    ]
  }
}