{
  "schemaVersion": "2.0",
  "generatedAt": "2025-08-14T18:02:44.596Z",
  "date": "20250815",
  "stadium": "02",
  "stadiumName": null,
  "race": "1R",
  "deadline": "2025-08-15 10:47:00",
  "gradeNumber": 5,
  "title": "第48回戸田ボート大賞・サンケイスポーツ杯",
  "subtitle": "予選",
  "distance": 1800,
  "entries": [
    {
      "lane": 1,
      "number": 5246,
      "name": "楠 将太郎",
      "classNumber": 3,
      "branchNumber": 11,
      "birthplaceNumber": 11,
      "age": 23,
      "weight": 52,
      "flyingCount": 1,
      "lateCount": 0,
      "avgST": 0.18,
      "natTop1": 4.82,
      "natTop2": 26.32,
      "natTop3": 49.47,
      "locTop1": 4.43,
      "locTop2": 26.04,
      "locTop3": 40.63,
      "motorNumber": 55,
      "motorTop2": 0,
      "motorTop3": 0,
      "boatNumber": 35,
      "boatTop2": 33.33,
      "boatTop3": 44.44
    },
    {
      "lane": 2,
      "number": 3807,
      "name": "岡部 哲",
      "classNumber": 3,
      "branchNumber": 11,
      "birthplaceNumber": 11,
      "age": 50,
      "weight": 51,
      "flyingCount": 0,
      "lateCount": 0,
      "avgST": 0.18,
      "natTop1": 4.84,
      "natTop2": 24.74,
      "natTop3": 42.27,
      "locTop1": 4.85,
      "locTop2": 24.51,
      "locTop3": 43.14,
      "motorNumber": 28,
      "motorTop2": 20,
      "motorTop3": 50,
      "boatNumber": 67,
      "boatTop2": 0,
      "boatTop3": 0
    },
    {
      "lane": 3,
      "number": 4532,
      "name": "秋元 哲",
      "classNumber": 1,
      "branchNumber": 11,
      "birthplaceNumber": 9,
      "age": 36,
      "weight": 52,
      "flyingCount": 0,
      "lateCount": 0,
      "avgST": 0.15,
      "natTop1": 7.22,
      "natTop2": 53.01,
      "natTop3": 77.11,
      "locTop1": 6.43,
      "locTop2": 46.28,
      "locTop3": 65.29,
      "motorNumber": 16,
      "motorTop2": 22.22,
      "motorTop3": 22.22,
      "boatNumber": 27,
      "boatTop2": 30,
      "boatTop3": 80
    },
    {
      "lane": 4,
      "number": 3589,
      "name": "西村 勝",
      "classNumber": 3,
      "branchNumber": 11,
      "birthplaceNumber": 11,
      "age": 51,
      "weight": 54.7,
      "flyingCount": 0,
      "lateCount": 0,
      "avgST": 0.17,
      "natTop1": 3.92,
      "natTop2": 17.57,
      "natTop3": 32.43,
      "locTop1": 5.14,
      "locTop2": 32.89,
      "locTop3": 48.68,
      "motorNumber": 63,
      "motorTop2": 0,
      "motorTop3": 0,
      "boatNumber": 30,
      "boatTop2": 11.11,
      "boatTop3": 22.22
    },
    {
      "lane": 5,
      "number": 4109,
      "name": "谷津 幸宏",
      "classNumber": 1,
      "branchNumber": 11,
      "birthplaceNumber": 11,
      "age": 45,
      "weight": 52.2,
      "flyingCount": 0,
      "lateCount": 0,
      "avgST": 0.12,
      "natTop1": 6.86,
      "natTop2": 52.07,
      "natTop3": 69.42,
      "locTop1": 6.02,
      "locTop2": 46.72,
      "locTop3": 59.84,
      "motorNumber": 10,
      "motorTop2": 66.67,
      "motorTop3": 66.67,
      "boatNumber": 24,
      "boatTop2": 14.29,
      "boatTop3": 14.29
    },
    {
      "lane": 6,
      "number": 3748,
      "name": "小黒 竜吾",
      "classNumber": 3,
      "branchNumber": 11,
      "birthplaceNumber": 11,
      "age": 50,
      "weight": 55.1,
      "flyingCount": 0,
      "lateCount": 0,
      "avgST": 0.18,
      "natTop1": 3.98,
      "natTop2": 14.74,
      "natTop3": 33.68,
      "locTop1": 4.52,
      "locTop2": 23.6,
      "locTop3": 40.45,
      "motorNumber": 22,
      "motorTop2": 11.11,
      "motorTop3": 33.33,
      "boatNumber": 14,
      "boatTop2": 40,
      "boatTop3": 70
    }
  ]
}